<!-- Netlist naming fix-up report --> 
<netlist>
	<blocks>
		<block previous="a[0]" current="a_0_"/>
		<block previous="a[1]" current="a_1_"/>
		<block previous="a[2]" current="a_2_"/>
		<block previous="a[3]" current="a_3_"/>
		<block previous="a[4]" current="a_4_"/>
		<block previous="a[5]" current="a_5_"/>
		<block previous="a[6]" current="a_6_"/>
		<block previous="a[7]" current="a_7_"/>
		<block previous="b[0]" current="b_0_"/>
		<block previous="b[1]" current="b_1_"/>
		<block previous="b[2]" current="b_2_"/>
		<block previous="b[3]" current="b_3_"/>
		<block previous="b[4]" current="b_4_"/>
		<block previous="b[5]" current="b_5_"/>
		<block previous="b[6]" current="b_6_"/>
		<block previous="b[7]" current="b_7_"/>
		<block previous="out:cout" current="out_cout"/>
		<block previous="out:sum[0]" current="out_sum_0_"/>
		<block previous="out:sum[1]" current="out_sum_1_"/>
		<block previous="out:sum[2]" current="out_sum_2_"/>
		<block previous="out:sum[3]" current="out_sum_3_"/>
		<block previous="out:sum[4]" current="out_sum_4_"/>
		<block previous="out:sum[5]" current="out_sum_5_"/>
		<block previous="out:sum[6]" current="out_sum_6_"/>
		<block previous="out:sum[7]" current="out_sum_7_"/>
		<block previous="sum[1]" current="sum_1_"/>
		<block previous="sum[2]" current="sum_2_"/>
		<block previous="$abc$291$new_n30_" current="_abc_291_new_n30_"/>
		<block previous="$abc$291$new_n31_" current="_abc_291_new_n31_"/>
		<block previous="sum[3]" current="sum_3_"/>
		<block previous="$abc$291$new_n33_" current="_abc_291_new_n33_"/>
		<block previous="sum[4]" current="sum_4_"/>
		<block previous="$abc$291$new_n35_" current="_abc_291_new_n35_"/>
		<block previous="sum[5]" current="sum_5_"/>
		<block previous="$abc$291$new_n37_" current="_abc_291_new_n37_"/>
		<block previous="$abc$291$new_n38_" current="_abc_291_new_n38_"/>
		<block previous="sum[6]" current="sum_6_"/>
		<block previous="sum[7]" current="sum_7_"/>
		<block previous="$abc$291$new_n41_" current="_abc_291_new_n41_"/>
		<block previous="$abc$291$new_n42_" current="_abc_291_new_n42_"/>
		<block previous="sum[0]" current="sum_0_"/>
	</blocks>
	<nets>
		<net previous="a[0]" current="a_0_"/>
		<net previous="a[1]" current="a_1_"/>
		<net previous="a[2]" current="a_2_"/>
		<net previous="a[3]" current="a_3_"/>
		<net previous="a[4]" current="a_4_"/>
		<net previous="a[5]" current="a_5_"/>
		<net previous="a[6]" current="a_6_"/>
		<net previous="a[7]" current="a_7_"/>
		<net previous="b[0]" current="b_0_"/>
		<net previous="b[1]" current="b_1_"/>
		<net previous="b[2]" current="b_2_"/>
		<net previous="b[3]" current="b_3_"/>
		<net previous="b[4]" current="b_4_"/>
		<net previous="b[5]" current="b_5_"/>
		<net previous="b[6]" current="b_6_"/>
		<net previous="b[7]" current="b_7_"/>
		<net previous="sum[0]" current="sum_0_"/>
		<net previous="sum[1]" current="sum_1_"/>
		<net previous="sum[2]" current="sum_2_"/>
		<net previous="sum[3]" current="sum_3_"/>
		<net previous="sum[4]" current="sum_4_"/>
		<net previous="sum[5]" current="sum_5_"/>
		<net previous="sum[6]" current="sum_6_"/>
		<net previous="sum[7]" current="sum_7_"/>
		<net previous="$abc$291$new_n31_" current="_abc_291_new_n31_"/>
		<net previous="$abc$291$new_n30_" current="_abc_291_new_n30_"/>
		<net previous="$abc$291$new_n33_" current="_abc_291_new_n33_"/>
		<net previous="$abc$291$new_n35_" current="_abc_291_new_n35_"/>
		<net previous="$abc$291$new_n38_" current="_abc_291_new_n38_"/>
		<net previous="$abc$291$new_n37_" current="_abc_291_new_n37_"/>
		<net previous="$abc$291$new_n42_" current="_abc_291_new_n42_"/>
		<net previous="$abc$291$new_n41_" current="_abc_291_new_n41_"/>
	</nets>
</netlist>
